graphrag_api/__init__.py
graphrag_api/common.py
graphrag_api/index.py
graphrag_api/search.py
graphrag_api-1.0.1.dist-info/LICENSE
graphrag_api-1.0.1.dist-info/METADATA
graphrag_api-1.0.1.dist-info/WHEEL
graphrag_api-1.0.1.dist-info/top_level.txt
graphrag_api-1.0.1.dist-info/RECORD
