Metadata-Version: 2.1
Name: graphrag_api
Version: 1.0.1
Summary: graphrag api 调用
Home-page: https://github.com/nightzjp/graphrag_api
Author: nightzjp
Author-email: seven.nighter@gmail.com
Classifier: Programming Language :: Python :: 3
Classifier: License :: OSI Approved :: MIT License
Classifier: Operating System :: OS Independent
Requires-Python: >=3.8
License-File: LICENSE
Requires-Dist: graphrag ==1.0.1
